HDPACKAGES/__init__.py
HDPACKAGES/python.py
compairingnumber-1.0.0.dist-info/LICENSE
compairingnumber-1.0.0.dist-info/METADATA
compairingnumber-1.0.0.dist-info/WHEEL
compairingnumber-1.0.0.dist-info/top_level.txt
compairingnumber-1.0.0.dist-info/RECORD
