Metadata-Version: 2.1
Name: compairingnumber
Version: 1.0.0
Summary: This function compair three number
Author: Harshavardhan Manoranjan Dhas
Author-email: dhasharsh@gmail.com
Requires-Python: >=3.6
License-File: LICENSE
